mutchecker/__init__.py
mutchecker/cli.py
mutchecker/config.py
mutchecker/versions.py
mutchecker/src/__init__.py
mutchecker/src/assem.py
mutchecker/src/bamstat.py
mutchecker/src/miniprot.py
mutchecker/src/pipeline.py
mutchecker/src/utils.py
mutchecker-0.0.5.dist-info/LICENSE
mutchecker-0.0.5.dist-info/METADATA
mutchecker-0.0.5.dist-info/WHEEL
mutchecker-0.0.5.dist-info/entry_points.txt
mutchecker-0.0.5.dist-info/top_level.txt
mutchecker-0.0.5.dist-info/RECORD
