Metadata-Version: 2.1
Name: mutchecker
Version: 0.0.5
Summary: Here's an example of a repository
Home-page: https://github.com/SouthernCD/mutchecker
Author: Yuxing Xu
Author-email: xuyuxing@mail.kib.ac.cn
Requires-Python: >=3.5
License-File: LICENSE
Requires-Dist: yxutil
Requires-Dist: yxseq
Requires-Dist: yxmath
Requires-Dist: numpy >=1.18.1
